namekox_kafka/__init__.py
namekox_kafka/constants.py
namekox_kafka/cli/__init__.py
namekox_kafka/cli/subctx/__init__.py
namekox_kafka/cli/subctx/kafkapub.py
namekox_kafka/core/__init__.py
namekox_kafka/core/messaging.py
namekox_kafka/core/producer.py
namekox_kafka/core/proxy.py
namekox_kafka/core/dependencies/__init__.py
namekox_kafka/core/dependencies/pub/__init__.py
namekox_kafka/core/entrypoints/__init__.py
namekox_kafka/core/entrypoints/sub/__init__.py
namekox_kafka/core/entrypoints/sub/handler.py
namekox_kafka-0.0.6.dist-info/LICENSE
namekox_kafka-0.0.6.dist-info/METADATA
namekox_kafka-0.0.6.dist-info/WHEEL
namekox_kafka-0.0.6.dist-info/top_level.txt
namekox_kafka-0.0.6.dist-info/zip-safe
namekox_kafka-0.0.6.dist-info/RECORD
